{
  "name": "Guilherme P. Krieck",
  "photo": "https://avatars.githubusercontent.com/u/116123096?v=4",
  "job": "Junior Developer",
  "location": "Severinia - SP",
  "phone": "(17) 99116-6969",
  "email": "guilherme.krieck@gmail.com",
  "github": "https://github.com/GuiKrieck",
  "linkedin": "https://www.linkedin.com/in/guilherme-krieck/",
  "skills": {
    "hardSkills": [
      {
        "name": "HTML",
        "logo": "https://guikrieck.github.io/Portfolio/data/imgs/html.png"
      },
      {
        "name": "CSS",
        "logo": "https://guikrieck.github.io/Portfolio/data/imgs/css.png"
      },
      {
        "name": "JavaScript",
        "logo": "https://guikrieck.github.io/Portfolio/data/imgs/js.png"
      },
      {
        "name": "TypeScript",
        "logo": "https://guikrieck.github.io/Portfolio/data/imgs/typescript.png"
      },
      {
        "name": "React",
        "logo": "https://guikrieck.github.io/Portfolio/data/imgs/react.png"
      }
    ],
    "softSkills": [
      "Facilidade em Aprender",
      "Organização",
      "Boa comunicação",
      "Trabalho em equipe",
      "Resolução de problemas"
    ]
  },
  "languages": [
    {
      "name":"Português",
      "level":"nativo"
    },
    {
      "name":"Inglês",
      "level":"fluente"
    }
  ],
  "portfolio": [
    {
      "name": "Alura-flix-T6-ONE",
      "repository":"https://github.com/GuiKrieck/Alura-flix-T6-ONE",
      "deploy":"https://alura-flix-t6-one.vercel.app/",
      "github": true
    },
    {
      "name": "React-Organo",
      "repository":"https://github.com/GuiKrieck/React-Organo",
      "deploy":"https://react-organo-peach.vercel.app/",
      "github": true
    },
    {
      "name": "AluraGeek-T6One",
      "repository":"https://github.com/GuiKrieck/AluraGeek-T6One",
      "deploy":"https://www.youtube.com/watch?v=ceer2a-ofWw",
      "github": true
    },
    {
      "name": "Challenge-Portfolio-T06One",
      "repository":"https://github.com/GuiKrieck/Challenge-Portfolio-T06One",
      "deploy":"https://guikrieck.github.io/Challenge-Portfolio-T06One/",
      "github": true
    },
    {
      "name": "HBOmax-clone-DIO",
      "repository":"https://github.com/GuiKrieck/HBOmax-clone-DIO",
      "deploy":"https://guikrieck.github.io/HBOmax-clone-DIO/",
      "github": true
    }
  ],
  "professionalExperience": [
    {
      "name": "Auxiliar de Contabilidade",
      "period": "Maio/2010 - Ago/2021",
      "company": "Método Contabilidade",
      "description": "Além de minhas reponsabilidades como Auxiliar de Contabilidade, vale ressaltar que fui o responsável pela automatização do escritório, migrando dos livros de papel para sistemas computadorizados. Também fui o responsável pelos treinamentos, cadastros, exclusões de novos empregados no sistema."
    }
  ],
  "education": [
    {
      "course": "Bacharel em Ciências Contábeis",
      "period": "Jan/2016 - Dez/2019",
      "school": "UNIP - EAD"
    },
    {
      "course": "Técnico em Informática",
      "period": "Jan/2005 - Jul/2006",
      "school": "Centro Paula Souza"
    }
  ],
  "one":[
    {
      "course": "FORMAÇÃO - React T6 - ONE",
      "certificate": "https://cursos.alura.com.br/degree/certificate/4f87b313-2595-4667-ac1e-6534dc3f9c43?lang",
      "isFinished": true   
    },
    {
      "course": "FORMAÇÃO - Front End T6 - ONE",
      "certificate": "https://cursos.alura.com.br/degree/certificate/f7684321-0f2e-42fb-b5bc-0f8743d102b5?lang",
      "isFinished": true    
    },
    {
      "course": "FORMAÇÃO - Iniciante em Programação T6 - ONE",
      "certificate": "https://cursos.alura.com.br/degree/certificate/5042e85e-06ac-4afa-8149-6100e54538b1?lang",
      "isFinished": true
    },
    {
      "course": "FORMAÇÃO - Desenvolvimento Pessoal T6 - ONE",
      "certificate": "https://cursos.alura.com.br/degree/certificate/a6be7d93-4c90-4f55-8b45-126024c87c33?lang",
      "isFinished": true
    },
    {
      "course": "FORMAÇÃO - Empreendedorismo, Agilidade e Protagonismo na Carreira T6 - ONE",
      "certificate": "https://cursos.alura.com.br/degree/certificate/ea832637-7f37-47b0-b33b-0b7f1ecf4ee6?lang",
      "isFinished": true
    }
  ],
  "dio":[
    {
      "course": "FORMAÇÃO - TypeScript Fullstack Developer",
      "certificate": "",
      "isFinished": false    
    },
    {
      "course": "FORMAÇÃO - React Developer",
      "certificate": "",
      "isFinished": false    
    },
    {
      "course": "FORMAÇÃO - JavaScript Developer",
      "certificate": "https://www.dio.me/certificate/QGIQ8OJT/share",
      "isFinished": true    
    },
    {
      "course": "FORMAÇÃO - CSS Web Developer",
      "certificate": "https://www.dio.me/certificate/HZOSX2RF/share",
      "isFinished": true
    },
    {
      "course": "FORMAÇÃO - HTML Web Developer",
      "certificate": "https://www.dio.me/certificate/WM2AMSZA/share",
      "isFinished": true
    }
  ]
}